tree_sitter_analyzer/TEST_IMPLEMENTATION_REPORT.md
tree_sitter_analyzer/TEST_IMPROVEMENT_TASKS.md
tree_sitter_analyzer/TEST_PHASE9_PLAN.md
tree_sitter_analyzer/__init__.py
tree_sitter_analyzer/__main__.py
tree_sitter_analyzer/api.py
tree_sitter_analyzer/cli_main.py
tree_sitter_analyzer/constants.py
tree_sitter_analyzer/encoding_utils.py
tree_sitter_analyzer/exceptions.py
tree_sitter_analyzer/file_handler.py
tree_sitter_analyzer/language_detector.py
tree_sitter_analyzer/language_loader.py
tree_sitter_analyzer/legacy_table_formatter.py
tree_sitter_analyzer/models.py
tree_sitter_analyzer/mypy_current_errors.txt
tree_sitter_analyzer/output_manager.py
tree_sitter_analyzer/project_detector.py
tree_sitter_analyzer/query_loader.py
tree_sitter_analyzer/cli/__init__.py
tree_sitter_analyzer/cli/__main__.py
tree_sitter_analyzer/cli/argument_validator.py
tree_sitter_analyzer/cli/info_commands.py
tree_sitter_analyzer/cli/commands/__init__.py
tree_sitter_analyzer/cli/commands/advanced_command.py
tree_sitter_analyzer/cli/commands/base_command.py
tree_sitter_analyzer/cli/commands/default_command.py
tree_sitter_analyzer/cli/commands/find_and_grep_cli.py
tree_sitter_analyzer/cli/commands/list_files_cli.py
tree_sitter_analyzer/cli/commands/partial_read_command.py
tree_sitter_analyzer/cli/commands/query_command.py
tree_sitter_analyzer/cli/commands/search_content_cli.py
tree_sitter_analyzer/cli/commands/structure_command.py
tree_sitter_analyzer/cli/commands/summary_command.py
tree_sitter_analyzer/cli/commands/table_command.py
tree_sitter_analyzer/core/__init__.py
tree_sitter_analyzer/core/analysis_engine.py
tree_sitter_analyzer/core/cache_service.py
tree_sitter_analyzer/core/engine_manager.py
tree_sitter_analyzer/core/parser.py
tree_sitter_analyzer/core/performance.py
tree_sitter_analyzer/core/query.py
tree_sitter_analyzer/core/query_filter.py
tree_sitter_analyzer/core/query_service.py
tree_sitter_analyzer/core/request.py
tree_sitter_analyzer/formatters/__init__.py
tree_sitter_analyzer-1.10.3.dist-info/METADATA
tree_sitter_analyzer-1.10.3.dist-info/WHEEL
tree_sitter_analyzer-1.10.3.dist-info/entry_points.txt
tree_sitter_analyzer-1.10.3.dist-info/licenses/LICENSE
tree_sitter_analyzer-1.10.3.dist-info/RECORD
