Metadata-Version: 2.4
Name: tree-sitter-analyzer
Version: 1.10.3
Summary: AI-era enterprise-grade code analysis tool with comprehensive HTML/CSS support, dynamic plugin architecture, and MCP integration
Project-URL: Homepage, https://github.com/aimasteracc/tree-sitter-analyzer
Project-URL: Documentation, https://github.com/aimasteracc/tree-sitter-analyzer#readme
Project-URL: Repository, https://github.com/aimasteracc/tree-sitter-analyzer.git
Project-URL: Issues, https://github.com/aimasteracc/tree-sitter-analyzer/issues
Project-URL: Changelog, https://github.com/aimasteracc/tree-sitter-analyzer/blob/main/CHANGELOG.md
Project-URL: Bug Reports, https://github.com/aimasteracc/tree-sitter-analyzer/issues
Project-URL: Source Code, https://github.com/aimasteracc/tree-sitter-analyzer
Author-email: "aisheng.yu" <aimasteracc@gmail.com>
Maintainer-email: "aisheng.yu" <aimasteracc@gmail.com>
License: MIT
License-File: LICENSE
Keywords: ai-tools,ast,code-analysis,css,html,mcp,mcp-server,model-context-protocol,multi-language,parsing,static-analysis,tree-sitter,web-development
Classifier: Development Status :: 4 - Beta
Classifier: Framework :: AsyncIO
Classifier: Intended Audience :: Developers
Classifier: License :: OSI Approved :: MIT License
Classifier: Operating System :: OS Independent
Classifier: Programming Language :: Python :: 3
Classifier: Programming Language :: Python :: 3.10
Classifier: Programming Language :: Python :: 3.11
Classifier: Programming Language :: Python :: 3.12
Classifier: Programming Language :: Python :: 3.13
Classifier: Topic :: Communications
Classifier: Topic :: Scientific/Engineering :: Artificial Intelligence
Classifier: Topic :: Software Development :: Code Generators
Classifier: Topic :: Software Development :: Libraries :: Python Modules
Classifier: Topic :: Software Development :: Quality Assurance
Classifier: Topic :: Text Processing :: Linguistic
Classifier: Typing :: Typed
Requires-Python: >=3.10
Requires-Dist: cachetools>=5.0.0
Requires-Dist: chardet>=5.0.0
Requires-Dist: deepdiff>=6.7.1
Requires-Dist: detect-secrets>=1.5.0
Requires-Dist: jsonschema>=4.0.0
Requires-Dist: mcp<2.0.0,>=1.12.3
Requires-Dist: psutil>=5.9.8
Requires-Dist: tree-sitter-c-sharp>=0.23.1
Requires-Dist: tree-sitter-c>=0.20.0
Requires-Dist: tree-sitter-cpp>=0.23.4
Requires-Dist: tree-sitter-css>=0.23.0
Requires-Dist: tree-sitter-go>=0.20.0
Requires-Dist: tree-sitter-html>=0.23.0
Requires-Dist: tree-sitter-java>=0.23.5
Requires-Dist: tree-sitter-javascript>=0.23.1
Requires-Dist: tree-sitter-kotlin>=0.3.0
Requires-Dist: tree-sitter-markdown>=0.3.1
Requires-Dist: tree-sitter-php>=0.24.1
Requires-Dist: tree-sitter-python>=0.23.6
Requires-Dist: tree-sitter-ruby>=0.23.1
Requires-Dist: tree-sitter-rust>=0.20.0
Requires-Dist: tree-sitter-sql>=0.3.11
Requires-Dist: tree-sitter-typescript>=0.23.2
Requires-Dist: tree-sitter-yaml>=0.7.0
Requires-Dist: tree-sitter>=0.25.0
Provides-Extra: all
Requires-Dist: anyio>=4.0.0; extra == 'all'
Requires-Dist: black>=24.0.0; extra == 'all'
Requires-Dist: httpx<1.0.0,>=0.27.0; extra == 'all'
Requires-Dist: isort>=5.13.0; extra == 'all'
Requires-Dist: mcp>=1.12.2; extra == 'all'
Requires-Dist: memory-profiler>=0.61.0; extra == 'all'
Requires-Dist: mypy>=1.17.0; extra == 'all'
Requires-Dist: pre-commit>=3.0.0; extra == 'all'
Requires-Dist: psutil<6,>=5.9.6; extra == 'all'
Requires-Dist: pydantic-settings>=2.2.1; extra == 'all'
Requires-Dist: pydantic>=2.5.0; extra == 'all'
Requires-Dist: pytest-asyncio>=1.1.0; extra == 'all'
Requires-Dist: pytest-cov>=4.0.0; extra == 'all'
Requires-Dist: pytest-mock>=3.14.1; extra == 'all'
Requires-Dist: pytest>=8.4.1; extra == 'all'
Requires-Dist: ruff>=0.5.0; extra == 'all'
Requires-Dist: tree-sitter-c<0.25.0,>=0.20.0; extra == 'all'
Requires-Dist: tree-sitter-cpp<0.25.0,>=0.23.4; extra == 'all'
Requires-Dist: tree-sitter-css<0.25.0,>=0.23.0; extra == 'all'
Requires-Dist: tree-sitter-go<0.25.0,>=0.20.0; extra == 'all'
Requires-Dist: tree-sitter-html<0.25.0,>=0.23.0; extra == 'all'
Requires-Dist: tree-sitter-java<0.25.0,>=0.23.5; extra == 'all'
Requires-Dist: tree-sitter-javascript<0.25.0,>=0.23.1; extra == 'all'
Requires-Dist: tree-sitter-markdown>=0.3.1; extra == 'all'
Requires-Dist: tree-sitter-python<0.25.0,>=0.23.0; extra == 'all'
Requires-Dist: tree-sitter-rust<0.25.0,>=0.20.0; extra == 'all'
Requires-Dist: tree-sitter-sql<0.4.0,>=0.3.11; extra == 'all'
Requires-Dist: tree-sitter-typescript<0.25.0,>=0.20.0; extra == 'all'
Requires-Dist: types-psutil>=5.9.0; extra == 'all'
Provides-Extra: all-languages
Requires-Dist: tree-sitter-c-sharp>=0.23.1; extra == 'all-languages'
Requires-Dist: tree-sitter-c<0.25.0,>=0.20.0; extra == 'all-languages'
Requires-Dist: tree-sitter-cpp<0.25.0,>=0.23.4; extra == 'all-languages'
Requires-Dist: tree-sitter-css<0.25.0,>=0.23.0; extra == 'all-languages'
Requires-Dist: tree-sitter-go<0.25.0,>=0.20.0; extra == 'all-languages'
Requires-Dist: tree-sitter-html<0.25.0,>=0.23.0; extra == 'all-languages'
Requires-Dist: tree-sitter-java<0.25.0,>=0.23.5; extra == 'all-languages'
Requires-Dist: tree-sitter-javascript<0.25.0,>=0.23.1; extra == 'all-languages'
Requires-Dist: tree-sitter-kotlin>=0.3.0; extra == 'all-languages'
Requires-Dist: tree-sitter-markdown>=0.3.1; extra == 'all-languages'
Requires-Dist: tree-sitter-php<0.25.0,>=0.23.0; extra == 'all-languages'
Requires-Dist: tree-sitter-python<0.25.0,>=0.23.0; extra == 'all-languages'
Requires-Dist: tree-sitter-ruby<0.25.0,>=0.23.0; extra == 'all-languages'
Requires-Dist: tree-sitter-rust<0.25.0,>=0.20.0; extra == 'all-languages'
Requires-Dist: tree-sitter-sql<0.4.0,>=0.3.11; extra == 'all-languages'
Requires-Dist: tree-sitter-typescript<0.25.0,>=0.20.0; extra == 'all-languages'
Requires-Dist: tree-sitter-yaml>=0.7.0; extra == 'all-languages'
Provides-Extra: c
Requires-Dist: tree-sitter-c<0.25.0,>=0.20.0; extra == 'c'
Provides-Extra: cpp
Requires-Dist: tree-sitter-cpp<0.25.0,>=0.23.4; extra == 'cpp'
Provides-Extra: csharp
Requires-Dist: tree-sitter-c-sharp>=0.23.1; extra == 'csharp'
Provides-Extra: css
Requires-Dist: tree-sitter-css<0.25.0,>=0.23.0; extra == 'css'
Provides-Extra: dev
Requires-Dist: black>=24.0.0; extra == 'dev'
Requires-Dist: hypothesis>=6.0.0; extra == 'dev'
Requires-Dist: isort>=5.13.0; extra == 'dev'
Requires-Dist: memory-profiler>=0.61.0; extra == 'dev'
Requires-Dist: mypy>=1.17.0; extra == 'dev'
Requires-Dist: pre-commit>=3.0.0; extra == 'dev'
Requires-Dist: psutil<6,>=5.9.6; extra == 'dev'
Requires-Dist: pytest-asyncio>=1.1.0; extra == 'dev'
Requires-Dist: pytest-cov>=4.0.0; extra == 'dev'
Requires-Dist: pytest-mock>=3.14.1; extra == 'dev'
Requires-Dist: pytest>=8.4.1; extra == 'dev'
Requires-Dist: ruff>=0.5.0; extra == 'dev'
Requires-Dist: types-psutil>=5.9.0; extra == 'dev'
Provides-Extra: full
Requires-Dist: anyio>=4.0.0; extra == 'full'
Requires-Dist: black>=24.0.0; extra == 'full'
Requires-Dist: httpx<1.0.0,>=0.27.0; extra == 'full'
Requires-Dist: isort>=5.13.0; extra == 'full'
Requires-Dist: mcp>=1.12.2; extra == 'full'
Requires-Dist: memory-profiler>=0.61.0; extra == 'full'
Requires-Dist: mypy>=1.17.0; extra == 'full'
Requires-Dist: pre-commit>=3.0.0; extra == 'full'
Requires-Dist: psutil<6,>=5.9.6; extra == 'full'
Requires-Dist: pydantic-settings>=2.2.1; extra == 'full'
Requires-Dist: pydantic>=2.5.0; extra == 'full'
Requires-Dist: pytest-asyncio>=1.1.0; extra == 'full'
Requires-Dist: pytest-cov>=4.0.0; extra == 'full'
Requires-Dist: pytest-mock>=3.14.1; extra == 'full'
Requires-Dist: pytest>=8.4.1; extra == 'full'
Requires-Dist: ruff>=0.5.0; extra == 'full'
Requires-Dist: tree-sitter-c<0.25.0,>=0.20.0; extra == 'full'
Requires-Dist: tree-sitter-cpp<0.25.0,>=0.23.4; extra == 'full'
Requires-Dist: tree-sitter-go<0.25.0,>=0.20.0; extra == 'full'
Requires-Dist: tree-sitter-java<0.25.0,>=0.23.5; extra == 'full'
Requires-Dist: tree-sitter-javascript<0.25.0,>=0.23.1; extra == 'full'
Requires-Dist: tree-sitter-markdown>=0.3.1; extra == 'full'
Requires-Dist: tree-sitter-python<0.25.0,>=0.23.0; extra == 'full'
Requires-Dist: tree-sitter-rust<0.25.0,>=0.20.0; extra == 'full'
Requires-Dist: tree-sitter-typescript<0.25.0,>=0.20.0; extra == 'full'
Requires-Dist: types-psutil>=5.9.0; extra == 'full'
Provides-Extra: go
Requires-Dist: tree-sitter-go<0.25.0,>=0.20.0; extra == 'go'
Provides-Extra: html
Requires-Dist: tree-sitter-html<0.25.0,>=0.23.0; extra == 'html'
Provides-Extra: integration
Requires-Dist: anyio>=4.0.0; extra == 'integration'
Requires-Dist: mcp>=1.12.2; extra == 'integration'
Requires-Dist: memory-profiler>=0.61.0; extra == 'integration'
Requires-Dist: psutil>=5.9.8; extra == 'integration'
Requires-Dist: pytest-asyncio>=0.21.0; extra == 'integration'
Requires-Dist: pytest-benchmark>=4.0.0; extra == 'integration'
Requires-Dist: pytest-cov>=4.0.0; extra == 'integration'
Requires-Dist: pytest-mock>=3.14.1; extra == 'integration'
Requires-Dist: pytest>=8.4.1; extra == 'integration'
Requires-Dist: tree-sitter-java>=0.23.5; extra == 'integration'
Requires-Dist: tree-sitter-javascript>=0.23.1; extra == 'integration'
Requires-Dist: tree-sitter-markdown>=0.3.1; extra == 'integration'
Requires-Dist: tree-sitter-python>=0.23.0; extra == 'integration'
Requires-Dist: tree-sitter-typescript>=0.20.0; extra == 'integration'
Provides-Extra: java
Requires-Dist: tree-sitter-java<0.25.0,>=0.23.5; extra == 'java'
Provides-Extra: javascript
Requires-Dist: tree-sitter-javascript<0.25.0,>=0.23.1; extra == 'javascript'
Provides-Extra: kotlin
Requires-Dist: tree-sitter-kotlin>=0.3.0; extra == 'kotlin'
Provides-Extra: markdown
Requires-Dist: tree-sitter-markdown>=0.3.1; extra == 'markdown'
Provides-Extra: mcp
Requires-Dist: anyio>=4.0.0; extra == 'mcp'
Requires-Dist: httpx<1.0.0,>=0.27.0; extra == 'mcp'
Requires-Dist: mcp>=1.12.2; extra == 'mcp'
Requires-Dist: pydantic-settings>=2.2.1; extra == 'mcp'
Requires-Dist: pydantic>=2.5.0; extra == 'mcp'
Provides-Extra: php
Requires-Dist: tree-sitter-php<0.25.0,>=0.23.0; extra == 'php'
Provides-Extra: popular
Requires-Dist: tree-sitter-java<0.25.0,>=0.23.5; extra == 'popular'
Requires-Dist: tree-sitter-javascript<0.25.0,>=0.23.1; extra == 'popular'
Requires-Dist: tree-sitter-python<0.25.0,>=0.23.0; extra == 'popular'
Requires-Dist: tree-sitter-typescript<0.25.0,>=0.20.0; extra == 'popular'
Provides-Extra: python
Requires-Dist: tree-sitter-python<0.25.0,>=0.23.0; extra == 'python'
Provides-Extra: ruby
Requires-Dist: tree-sitter-ruby<0.25.0,>=0.23.0; extra == 'ruby'
Provides-Extra: rust
Requires-Dist: tree-sitter-rust<0.25.0,>=0.20.0; extra == 'rust'
Provides-Extra: sql
Requires-Dist: tree-sitter-sql<0.4.0,>=0.3.11; extra == 'sql'
Provides-Extra: systems
Requires-Dist: tree-sitter-c<0.25.0,>=0.20.0; extra == 'systems'
Requires-Dist: tree-sitter-cpp<0.25.0,>=0.23.4; extra == 'systems'
Requires-Dist: tree-sitter-go<0.25.0,>=0.20.0; extra == 'systems'
Requires-Dist: tree-sitter-rust<0.25.0,>=0.20.0; extra == 'systems'
Provides-Extra: test
Requires-Dist: pytest-asyncio>=1.1.0; extra == 'test'
Requires-Dist: pytest-cov>=4.0.0; extra == 'test'
Requires-Dist: pytest-mock>=3.14.1; extra == 'test'
Requires-Dist: pytest>=8.4.1; extra == 'test'
Requires-Dist: tree-sitter-c-sharp>=0.23.1; extra == 'test'
Requires-Dist: tree-sitter-cpp>=0.23.4; extra == 'test'
Requires-Dist: tree-sitter-java>=0.23.5; extra == 'test'
Requires-Dist: tree-sitter-javascript>=0.23.1; extra == 'test'
Requires-Dist: tree-sitter-php<0.25.0,>=0.23.0; extra == 'test'
Requires-Dist: tree-sitter-python>=0.23.0; extra == 'test'
Requires-Dist: tree-sitter-ruby<0.25.0,>=0.23.0; extra == 'test'
Requires-Dist: tree-sitter-sql<0.4.0,>=0.3.11; extra == 'test'
Provides-Extra: typescript
Requires-Dist: tree-sitter-typescript<0.25.0,>=0.20.0; extra == 'typescript'
Provides-Extra: web
Requires-Dist: tree-sitter-css<0.25.0,>=0.23.0; extra == 'web'
Requires-Dist: tree-sitter-html<0.25.0,>=0.23.0; extra == 'web'
Requires-Dist: tree-sitter-javascript<0.25.0,>=0.23.1; extra == 'web'
Requires-Dist: tree-sitter-php<0.25.0,>=0.23.0; extra == 'web'
Requires-Dist: tree-sitter-ruby<0.25.0,>=0.23.0; extra == 'web'
Requires-Dist: tree-sitter-typescript<0.25.0,>=0.20.0; extra == 'web'
Provides-Extra: yaml
Requires-Dist: tree-sitter-yaml>=0.7.0; extra == 'yaml'
